vnpy_udata/__init__.py
vnpy_udata/udata_datafeed.py
vnpy_udata-2023.3.1.dist-info/LICENSE
vnpy_udata-2023.3.1.dist-info/METADATA
vnpy_udata-2023.3.1.dist-info/WHEEL
vnpy_udata-2023.3.1.dist-info/top_level.txt
vnpy_udata-2023.3.1.dist-info/RECORD
